psalm/__init__.py
psalm/psalm.py
psalm/viz_utils.py
protein_sequence_annotation-1.1.3.dist-info/METADATA
protein_sequence_annotation-1.1.3.dist-info/WHEEL
protein_sequence_annotation-1.1.3.dist-info/top_level.txt
protein_sequence_annotation-1.1.3.dist-info/RECORD
