Metadata-Version: 2.4
Name: protein_sequence_annotation
Version: 1.1.3
Summary: Protein sequence annotation with language models
Home-page: https://github.com/Protein-Sequence-Annotation/PSALM
Author: Arpan Sarkar & Kumaresh Krishnan
Author-email: arpan_sarkar@g.harvard.edu
License: CC by 4.0
Requires-Python: >=3.10
Requires-Dist: huggingface-hub>=0.23.2
Requires-Dist: safetensors>=0.4.3
Requires-Dist: fair-esm>=2.0.0
Requires-Dist: matplotlib>=3.8.2
Requires-Dist: biopython>=1.83
Dynamic: author
Dynamic: author-email
Dynamic: description
Dynamic: description-content-type
Dynamic: home-page
Dynamic: license
Dynamic: requires-dist
Dynamic: requires-python
Dynamic: summary
